tap_belvo/__init__.py
tap_belvo/__main__.py
tap_belvo/client.py
tap_belvo/openapi.json
tap_belvo/tap.py
tap_belvo/streams/__init__.py
tap_belvo/streams/banking.py
tap_belvo/streams/core.py
tap_belvo/streams/enrichment.py
tap_belvo/streams/fiscal.py
tap_belvo-0.3.3.dist-info/METADATA
tap_belvo-0.3.3.dist-info/WHEEL
tap_belvo-0.3.3.dist-info/entry_points.txt
tap_belvo-0.3.3.dist-info/licenses/LICENSE
tap_belvo-0.3.3.dist-info/RECORD
