Metadata-Version: 2.4
Name: tap-belvo
Version: 0.3.3
Summary: Singer tap for Belvo, built with the Meltano SDK for Singer Taps.
Project-URL: Documentation, https://github.com/reservoir-data/tap-belvo#readme
Project-URL: Homepage, https://github.com/reservoir-data/tap-belvo
Project-URL: Source, https://github.com/reservoir-data/tap-belvo
Author-email: Edgar Ramírez-Mondragón <edgarrm358@gmail.com>
Maintainer-email: Edgar Ramírez-Mondragón <edgarrm358@gmail.com>
License-Expression: Apache-2.0
License-File: LICENSE
Keywords: Belvo,ELT,singer.io
Classifier: Programming Language :: Python :: 3 :: Only
Classifier: Programming Language :: Python :: 3.11
Classifier: Programming Language :: Python :: 3.12
Classifier: Programming Language :: Python :: 3.13
Classifier: Programming Language :: Python :: 3.14
Requires-Python: >=3.11
Requires-Dist: requests-cache==1.*
Requires-Dist: requests~=2.32.3
Requires-Dist: singer-sdk~=0.51.0
Requires-Dist: typing-extensions>=4.15; python_full_version < '3.12'
